zensols/mimic/resources/app.conf
zensols/mimic/resources/decorator.conf
zensols/mimic/resources/default.conf
zensols/mimic/resources/obj.conf
zensols/mimic/resources/postgres.conf
zensols/mimic/resources/table-overview.csv
zensols/mimic/resources/conf/corpus.conf
zensols/mimic/resources/conf/lang.conf
zensols/mimic/resources/conf/note.conf
zensols/mimic/resources/conf/persist.conf
zensols/mimic/resources/conf/remove-space.conf
zensols/mimic/resources/postgres/admission.sql
zensols/mimic/resources/postgres/icd.sql
zensols/mimic/resources/postgres/medications.sql
zensols/mimic/resources/postgres/note.sql
zensols/mimic/resources/postgres/patient.sql
zensols/mimic/resources/sqlite/admission.sql
zensols/mimic/resources/sqlite/icd.sql
zensols/mimic/resources/sqlite/medications.sql
zensols/mimic/resources/sqlite/note.sql
zensols/mimic/resources/sqlite/patient.sql
zensols/mimic/__init__.py
zensols/mimic/adm.py
zensols/mimic/app.py
zensols/mimic/cli.py
zensols/mimic/corpus.py
zensols/mimic/domain.py
zensols/mimic/note.py
zensols/mimic/parafac.py
zensols/mimic/persist.py
zensols/mimic/regexnote.py
zensols/mimic/tokenizer.py
zensols_mimic-1.9.2.dist-info/METADATA
zensols_mimic-1.9.2.dist-info/WHEEL
zensols_mimic-1.9.2.dist-info/entry_points.txt
zensols_mimic-1.9.2.dist-info/licenses/LICENSE.md
zensols_mimic-1.9.2.dist-info/RECORD
