Metadata-Version: 2.3
Name: zensols_mimic
Version: 1.9.2
Summary: A utility library for parsing the MIMIC-III corpus
Project-URL: Homepage, https://github.com/plandes/mimic
Project-URL: Documentation, https://plandes.github.io/mimic
Project-URL: Repository, https://github.com/plandes/mimic.git
Project-URL: Issues, https://github.com/plandes/mimic/issues
Project-URL: Changelog, https://github.com/plandes/mimic/blob/master/CHANGELOG.md
Author-email: Paul Landes <landes@mailc.net>
License: MIT
Keywords: clinical,mimic,natural language processing
Requires-Python: <3.13,>=3.11
Requires-Dist: pillow~=10.1.0
Requires-Dist: zensols-db~=1.4.1
Requires-Dist: zensols-mednlp~=1.9.2
